{
  "timestamp": "2026-03-26T20:20:05.000Z",
  "version": "5.30 Alpha",
  "modules": [
    {
      "name": "Estúdio de Conteúdo",
      "status": "✅ ONLINE",
      "details": "DOM: true | Init: true"
    },
    {
      "name": "Execução e Metas",
      "status": "✅ ONLINE",
      "details": "DOM: true | Init: true"
    },
    {
      "name": "Inteligência de Tráfego",
      "status": "✅ ONLINE",
      "details": "DOM: true | Init: true"
    },
    {
      "name": "Assistente de Apoio",
      "status": "✅ ONLINE",
      "details": "DOM: true | Init: true"
    },
    {
      "name": "Arquitetura de Conteúdo",
      "status": "✅ ONLINE",
      "details": "DOM: true | Init: true"
    },
    {
      "name": "Curadoria e Aprovação",
      "status": "✅ ONLINE",
      "details": "DOM: true | Init: true"
    }
  ],
  "apis": [
    {
      "name": "Gemini Hub",
      "status": "✅ CONECTADO",
      "latency": "13ms"
    },
    {
      "name": "Media Assets",
      "status": "✅ CONECTADO",
      "latency": "3ms"
    },
    {
      "name": "Strategic Analytics",
      "status": "✅ CONECTADO",
      "latency": "1071ms"
    },
    {
      "name": "Drafts Storage",
      "status": "✅ CONECTADO",
      "latency": "235ms"
    }
  ],
  "logs": [
    {
      "type": "log",
      "msg": "🤖 ChatApp (Abidos V4) Initialized.",
      "time": "17:07:02"
    },
    {
      "type": "log",
      "msg": "🧠 NeuroEngine Copilot Initialized",
      "time": "17:07:02"
    },
    {
      "type": "log",
      "msg": "🧠 Neuro-Training: Motor de Conversa Contínua v2.0 inicializado.",
      "time": "17:07:02"
    },
    {
      "type": "log",
      "msg": "🌳 Inicializando Gestor de Menus e Silos...",
      "time": "17:07:02"
    },
    {
      "type": "log",
      "msg": "📂 [neuroAPI] Sincronizando Acervo...",
      "time": "17:07:02"
    },
    {
      "type": "log",
      "msg": "📊 Marketing Lab Inicializado. Carregando estado persistente...",
      "time": "17:07:02"
    },
    {
      "type": "log",
      "msg": "👑 [MANAGER AGENT] Inicializando Orquestrador Central...",
      "time": "17:07:02"
    },
    {
      "type": "log",
      "msg": "🧠 [STUDIO] Missão Step-by-Step Iniciada...",
      "time": "17:07:02"
    },
    {
      "type": "log",
      "msg": "💓 [PULSO] Monitor de Latência Ativado.",
      "time": "17:07:02"
    },
    {
      "type": "log",
      "msg": "🚀 [Núcleo de Marketing] App Core Initialized.",
      "time": "17:07:02"
    },
    {
      "type": "log",
      "msg": "✨ [SPARK] Motor de Orquestração Inicializado.",
      "time": "17:07:02"
    },
    {
      "type": "log",
      "msg": "📡 Conectado ao Fluxo de Log Real-time.",
      "time": "17:07:02"
    },
    {
      "type": "log",
      "msg": "📂 [neuroAPI] Sincronizando inventário com o Acervo Vercel...",
      "time": "17:07:03"
    },
    {
      "type": "log",
      "msg": "📂 [neuroAPI] Sincronizando Acervo...",
      "time": "17:07:03"
    },
    {
      "type": "log",
      "msg": "✅ 6 páginas detectadas no Next.js.",
      "time": "17:07:03"
    },
    {
      "type": "error",
      "msg": "Erro PSI (Cache): Falha na auditoria PSI: Quota exceeded for quota metric 'Queries' and limit 'Queries per day' of service 'pagespeedonline.googleapis.com' for consumer 'project_number:583797351490'.",
      "time": "17:07:05"
    },
    {
      "type": "log",
      "msg": "💾 [HEALTH] Relatório Longitudinal Salvo com Sucesso.",
      "time": "17:07:07"
    }
  ]
}